linex2/GenerateLipidNetwork.py
linex2/LipidNetwork.py
linex2/__init__.py
linex2/_network_analysis.py
linex2/_network_compute_statistics.py
linex2/_network_lipid_utils.py
linex2/_network_lipidome_summary.py
linex2/colour_helper.py
linex2/edgelist.py
linex2/exceptions.py
linex2/libAP_nx.py
linex2/lipid.py
linex2/load_data.py
linex2/misc.py
linex2/parser.py
linex2/reaction.py
linex2/reaction_evaluation.py
linex2/reaction_types.py
linex2/reference.py
linex2/tmp_dirty_functions.py
linex2/utils.py
linex2/validation.py
linex2/vis_utils.py
linex2/data/Reactome_ConnectionOfReactionsToMolecule_all.csv
linex2/data/Reactome_Others_all_unique.csv
linex2/data/Reactome_ReactionDetailsEnzyme_all.csv
linex2/data/Reactome_reactions_for_curation.csv
linex2/data/Rhea_ConnectionOfReactionsToMolecule_all.csv
linex2/data/Rhea_GeneName_mapping.csv
linex2/data/Rhea_Others_all_unique.csv
linex2/data/Rhea_ReactionDetailsEnzyme.csv
linex2/data/Rhea_reactions_for_curation.csv
linex2/data/__init__.py
linex2/data/citing_data.txt
linex2/data/default_fatty_acids.txt
linex2/data/standard_lipid_classes.csv
linex2/templates/__init__.py
linex2/templates/lipid_colours.json
linex2/templates/vis_dynamic.html
linex2/templates/vis_main.html
linex2-1.1.16.dist-info/LICENSE.txt
linex2-1.1.16.dist-info/METADATA
linex2-1.1.16.dist-info/WHEEL
linex2-1.1.16.dist-info/top_level.txt
linex2-1.1.16.dist-info/RECORD
