Metadata-Version: 2.1
Name: linex2
Version: 1.1.16
Summary: Lipid Network Explorer 2 (LINEX2) package. Python backend to the LINEX web-app
Home-page: https://exbio.wzw.tum.de/linex/
Author: Tim Daniel Rose, Nikolai Koehler, Olga Lazareva, Josch Konstantin Pauling
Author-email: tim.rose@tum.de, nikolai.koehler@tum.de
License: AGPLv3
Project-URL: Source, https://gitlab.lrz.de/lipitum-projects/linex2_package
Project-URL: Publication, https://doi.org/10.1093/bib/bbac572
Classifier: License :: OSI Approved :: GNU Affero General Public License v3
Classifier: Topic :: Scientific/Engineering :: Bio-Informatics
Classifier: Intended Audience :: Science/Research
Classifier: Natural Language :: English
Classifier: Operating System :: MacOS
Classifier: Operating System :: Microsoft :: Windows
Classifier: Operating System :: POSIX :: Linux
Classifier: Programming Language :: Python :: 3
Requires-Python: >=3.8
License-File: LICENSE.txt
Requires-Dist: networkx
Requires-Dist: pandas
Requires-Dist: matplotlib
Requires-Dist: numpy
Requires-Dist: pyvis
Requires-Dist: scikit-learn
Requires-Dist: statsmodels
Requires-Dist: jinja2
Requires-Dist: seaborn
